{
    "asterion": {
        "data_atual": {
            "ano": 580,
            "mes": 0,
            "dia": 9
        },
        "config": {
            "meses": [
                "ar"
            ],
            "dias_por_mes": [
                10
            ],
            "estacoes": [
                {
                    "nome": "inv",
                    "inicio": 1,
                    "fim": 5
                },
                {
                    "nome": "ver",
                    "inicio": 6,
                    "fim": 10
                }
            ],
            "luas": [
                {
                    "nome": "ki",
                    "ciclo": 5
                },
                {
                    "nome": "kl",
                    "ciclo": 10
                }
            ]
        }
    }
}